cache/__init__.py
cache/cache.py
alib_py-0.1.0.dist-info/LICENSE
alib_py-0.1.0.dist-info/METADATA
alib_py-0.1.0.dist-info/WHEEL
alib_py-0.1.0.dist-info/top_level.txt
alib_py-0.1.0.dist-info/RECORD
